[{"icon": "mnk/anatman.png", "name": "Anatman"}, {"icon": "mnk/arm's_length.png", "name": "Arm'S Length"}, {"icon": "mnk/arm_of_the_destroyer.png", "name": "Arm Of The Destroyer"}, {"icon": "mnk/bloodbath.png", "name": "Bloodbath"}, {"icon": "mnk/bootshine.png", "name": "Bootshine"}, {"icon": "mnk/brotherhood.png", "name": "Brotherhood"}, {"icon": "mnk/celestial_revolution.png", "name": "Celestial Revolution"}, {"icon": "mnk/demolish.png", "name": "Demolish"}, {"icon": "mnk/dragon_kick.png", "name": "Dragon Kick"}, {"icon": "mnk/elixir_field.png", "name": "Elixir Field"}, {"icon": "mnk/enlightenment.png", "name": "Enlightenment"}, {"icon": "mnk/feint.png", "name": "Feint"}, {"icon": "mnk/flint_strike.png", "name": "Flint Strike"}, {"icon": "mnk/form_shift.png", "name": "Form Shift"}, {"icon": "mnk/four-point_fury.png", "name": "Four-Point Fury"}, {"icon": "mnk/howling_fist.png", "name": "Howling Fist"}, {"icon": "mnk/leg_sweep.png", "name": "Leg Sweep"}, {"icon": "mnk/mantra.png", "name": "Mantra"}, {"icon": "mnk/masterful_blitz.png", "name": "Masterful Blitz"}, {"icon": "mnk/meditation.png", "name": "Meditation"}, {"icon": "mnk/perfect_balance.png", "name": "Perfect Balance"}, {"icon": "mnk/phantom_rush.png", "name": "Phantom Rush"}, {"icon": "mnk/riddle_of_earth.png", "name": "Riddle Of Earth"}, {"icon": "mnk/riddle_of_fire.png", "name": "Riddle Of Fire"}, {"icon": "mnk/riddle_of_wind.png", "name": "Riddle Of Wind"}, {"icon": "mnk/rising_phoenix.png", "name": "Rising Phoenix"}, {"icon": "mnk/rockbreaker.png", "name": "Rockbreaker"}, {"icon": "mnk/second_wind.png", "name": "Second Wind"}, {"icon": "mnk/shadow_of_the_destroyer.png", "name": "Shadow Of The Destroyer"}, {"icon": "mnk/six-sided_star.png", "name": "Six-Sided Star"}, {"icon": "mnk/snap_punch.png", "name": "Snap Punch"}, {"icon": "mnk/steel_peak.png", "name": "Steel Peak"}, {"icon": "mnk/the_forbidden_chakra.png", "name": "The Forbidden Chakra"}, {"icon": "mnk/thunderclap.png", "name": "Thunderclap"}, {"icon": "mnk/tornado_kick.png", "name": "Tornado Kick"}, {"icon": "mnk/true_north.png", "name": "True North"}, {"icon": "mnk/true_strike.png", "name": "True Strike"}, {"icon": "mnk/twin_snakes.png", "name": "Twin Snakes"}]